tplink_wr/__init__.py
tplink_wr/exceptions.py
tplink_wr/router.py
tplink_wr/fetchers/__init__.py
tplink_wr/fetchers/dhcp.py
tplink_wr/fetchers/fetcher.py
tplink_wr/fetchers/status.py
tplink_wr/fetchers/wlan.py
tplink_wr/parse/__init__.py
tplink_wr/parse/html.py
tplink_wr/parse/js.py
tplink_wr/parse/utils.py
tplink_wr_api-0.2.1.dist-info/LICENSE
tplink_wr_api-0.2.1.dist-info/METADATA
tplink_wr_api-0.2.1.dist-info/WHEEL
tplink_wr_api-0.2.1.dist-info/top_level.txt
tplink_wr_api-0.2.1.dist-info/RECORD
